mcodegpthippa/__init__.py
mcodegpthippa/cli.py
mcodegpthippa/clients/__init__.py
mcodegpthippa/clients/hfhub_client.py
mcodegpthippa/clients/openai_client.py
mcodegpthippa/clients/pubmed_client.py
mcodegpthippa/clients/soup_client.py
mcodegpthippa/clients/wikipedia_client.py
mcodegpthippa/conf/synonymizer-conf.yaml
mcodegpthippa/converters/__init__.py
mcodegpthippa/converters/ontology_converter.py
mcodegpthippa/engines/__init__.py
mcodegpthippa/engines/embedding_similarity_engine.py
mcodegpthippa/engines/enrichment.py
mcodegpthippa/engines/generic_engine.py
mcodegpthippa/engines/gpt4all_engine.py
mcodegpthippa/engines/halo_engine.py
mcodegpthippa/engines/hfhub_engine.py
mcodegpthippa/engines/knowledge_engine.py
mcodegpthippa/engines/mapping_engine.py
mcodegpthippa/engines/pheno_engine.py
mcodegpthippa/engines/reasoner_engine.py
mcodegpthippa/engines/resolver.py
mcodegpthippa/engines/spires_engine.py
mcodegpthippa/engines/synonym_engine.py
mcodegpthippa/evaluation/__init__.py
mcodegpthippa/evaluation/ctd/__init__.py
mcodegpthippa/evaluation/ctd/database/CDR_TestSet.BioC.xml.gz
mcodegpthippa/evaluation/ctd/database/CDR_TrainSet.BioC.xml.gz
mcodegpthippa/evaluation/ctd/database/synonyms.yaml
mcodegpthippa/evaluation/ctd/eval_ctd.py
mcodegpthippa/evaluation/drugmechdb/__init__.py
mcodegpthippa/evaluation/drugmechdb/datamodel/drugmechdb.py
mcodegpthippa/evaluation/drugmechdb/datamodel/drugmechdb.yaml
mcodegpthippa/evaluation/drugmechdb/eval_drugmechdb.py
mcodegpthippa/evaluation/enrichment/__init__.py
mcodegpthippa/evaluation/enrichment/eval_enrichment.py
mcodegpthippa/evaluation/evaluation_engine.py
mcodegpthippa/evaluation/go/eval_go.py
mcodegpthippa/evaluation/hpoa/__init__.py
mcodegpthippa/evaluation/hpoa/eval_hpoa.py
mcodegpthippa/evaluation/ibd/Abstracts/10338374.txt
mcodegpthippa/evaluation/ibd/Abstracts/17653185.txt
mcodegpthippa/evaluation/ibd/Abstracts/18253950.txt
mcodegpthippa/evaluation/ibd/Abstracts/24104886.txt
mcodegpthippa-0.2.21.dist-info/LICENSE
mcodegpthippa-0.2.21.dist-info/METADATA
mcodegpthippa-0.2.21.dist-info/WHEEL
mcodegpthippa-0.2.21.dist-info/entry_points.txt
mcodegpthippa-0.2.21.dist-info/RECORD
