Metadata-Version: 2.1
Name: mcodegpthippa
Version: 0.2.21
Summary: mcodegpthippa
License: BSD-3
Author: Kai Zhang
Author-email: kai.zhang.1@uth.tmc.edu
Requires-Python: >=3.9, !=2.7.*, !=3.0.*, !=3.1.*, !=3.2.*, !=3.3.*, !=3.4.*, !=3.5.*, !=3.6.*, !=3.7.*, !=3.8.*
Classifier: License :: Other/Proprietary License
Classifier: Programming Language :: Python :: 3
Classifier: Programming Language :: Python :: 3.9
Classifier: Programming Language :: Python :: 3.10
Classifier: Programming Language :: Python :: 3.11
Provides-Extra: docs
Provides-Extra: gpt4all
Provides-Extra: huggingface
Provides-Extra: recipes
Provides-Extra: textract
Provides-Extra: web
Requires-Dist: Jinja2 (>=3.1.2) ; extra == "web"
Requires-Dist: aiohttp (>=3.8.4)
Requires-Dist: airium (>=0.2.5)
Requires-Dist: beautifulsoup4 (>=4.11.1)
Requires-Dist: bioc (>=2.0.post5)
Requires-Dist: cachier (>=2.1.0)
Requires-Dist: class-resolver (>=0.4.2)
Requires-Dist: click (>=8.1.3)
Requires-Dist: eutils (>=0.6.0)
Requires-Dist: fastapi (>=0.88.0) ; extra == "web"
Requires-Dist: gilda (>=1.0.0)
Requires-Dist: gpt4 (>=0.0.1)
Requires-Dist: httpx (>=0.23.3)
Requires-Dist: huggingface_hub[huggingface] (>=0.15.1) ; extra == "huggingface"
Requires-Dist: inflect (>=6.0.2)
Requires-Dist: inflection (>=0.5.1)
Requires-Dist: jsonlines (>=3.1.0)
Requires-Dist: keyring (>=24.2.0,<25.0.0)
Requires-Dist: linkml (>=1.5.6,<2.0.0)
Requires-Dist: linkml-owl (>=0.3.0,<0.4.0)
Requires-Dist: llm (>=0.6.1,<0.7.0)
Requires-Dist: llm-gpt4all (>=0.1.1,<0.2.0)
Requires-Dist: myst-parser[docs] (>=0.18.1) ; extra == "docs"
Requires-Dist: nlpcloud (>=1.0.39)
Requires-Dist: oaklib (>=0.5.15)
Requires-Dist: openai (>=0.27.8)
Requires-Dist: pystow (>=0.5.0,<0.6.0)
Requires-Dist: python-multipart (>=0.0.5,<0.0.6)
Requires-Dist: recipe-scrapers[recipes] (>=14.35.0) ; extra == "recipes"
Requires-Dist: requests (>=2.31.0,<3.0.0)
Requires-Dist: requests-cache (>=1.0.1)
Requires-Dist: ruamel.yaml (>=0.17.31)
Requires-Dist: sphinx-autodoc-typehints[docs] (>=1.19.4) ; extra == "docs"
Requires-Dist: sphinx-click[docs] (>=4.3.0) ; extra == "docs"
Requires-Dist: sphinx-rtd-theme[docs] (>=1.0.0) ; extra == "docs"
Requires-Dist: sphinx[docs] (>=5.3.0) ; extra == "docs"
Requires-Dist: streamlit (>=1.22.0)
Requires-Dist: textract[textract] ; extra == "textract"
Requires-Dist: tiktoken (>=0.3.3)
Requires-Dist: uvicorn (>=0.20.0) ; extra == "web"
Requires-Dist: wikipedia (>=1.4.0)
Requires-Dist: wikipedia-api (>=0.5.8)
